{"config_hash": "21a25e48dd351a4f", "entry": {"domain": "Pre-Kantian rationalism and empiricism", "subtopic": "Deduction", "tier": "state", "tier_label": "Arkansas", "state_abbr": "AR", "tier_population": 3011524, "depth": 2, "reasoning": "### Part 1 — Investigation\n\n**1. Current Understanding**  \nThe concept of *deduction* in pre-Kantian rationalism and empiricism is fundamentally shaped by divergent epistemological commitments:  \n\n- **Rationalism (Descartes, Spinoza, Leibniz)**: Deduction is understood as *a priori* reasoning from self-evident first principles (e.g., innate ideas, clear and distinct perceptions, logical axioms) to necessary truths. For Descartes, deduction mirrors geometric proof—rigorous, deductive chains from indubitable foundations. Spinoza’s *geometrical method* in the *Ethics* exemplifies deduction as the derivation of metaphysical and ethical truths from definitions and axioms. Leibniz extends this to a general *calculus ratiocinator*, envisioning deduction as a formalizable, algorithmic process for resolving disputes.  \n\n- **Empiricism (Locke, Berkeley, Hume)**: Deduction is reconceived as *a posteriori* or *hypothetical*, subordinate to inductive generalization from experience. Locke distinguishes *real* (empirical) from *verbal* (nominal) deduction, emphasizing that knowledge of external reality cannot be deduced *a priori* but must be inferred from sensory data. Hume radicalizes this: causal reasoning—often mistaken for deduction—is nothing but *customary association*; there is no rational deduction of cause-effect necessity, only probabilistic expectation.  \n\nThus, “deduction” is not a monolithic method but a contested site where rationalists defend its foundational role and empiricists restrict or reject it as a source of substantive knowledge.\n\n**2. Key Challenges or Tensions**  \n- **Foundationalism vs. Skepticism**: Rationalists assume deductive certainty rests on indubitable foundations; empiricists (especially Hume) undermine this by showing even apparent first principles (e.g., identity, causality) lack deductive justification.  \n- **Methodological Incommensurability**: Rationalist deduction assumes a privileged access to *a priori* truths (e.g., God’s non-deceptiveness, innate ideas); empiricists deny such access, demanding empirical verification or reducing deduction to formal logic (e.g., Hume’s “relations of ideas”).  \n- **The Problem of Apriority**: How can *a priori* knowledge be justified without falling into dogmatism (rationalism) or skepticism (empiricism)? Kant’s later “Copernican turn” arises directly from this tension.  \n- **Historical Anachronism Risk**: Attaching modern formal logic (e.g., truth-functional deduction) to early modern thinkers distorts their actual usage, where “deduction” often meant *derivation* or *explanation*, not syntactic inference.\n\n**3. Best Approaches**  \n- **Textual Fidelity**: Analyze the term *deductio* and related terms (*derivation*, *inference*, *reasoning*) in context, attending to rhetorical and epistemological functions (e.g., Descartes’ *Meditations* vs. Spinoza’s *Ethics* vs. Hume’s *Treatise*).  \n- **Historical Contextualization**: Situate debates within broader intellectual currents—e.g., post-Reformation skepticism, the rise of Newtonian natural philosophy, the decline of Aristotelian scholasticism.  \n- **Conceptual Precision**: Distinguish:  \n  - *Logical deduction* (valid inference from premises)  \n  - *Epistemic deduction* (justification of beliefs via necessary reasoning)  \n  - *Metaphysical deduction* (explanation of being from first causes)  \n- **Comparative Methodology**: Contrast rationalist and empiricist accounts of deduction *within* their own frameworks before projecting Kantian critiques.\n\n**4. Practical Steps**  \n1. **Source Selection**: Core texts: Descartes’ *Meditations* and *Principles of Philosophy*; Spinoza’s *Ethics*; Leibniz’s *New Essays* and *Discourse on Metaphysics*; Locke’s *Essay* (especially Book IV); Berkeley’s *Principles*; Hume’s *Treatise* (Book I) and *Enquiry Concerning Human Understanding*.  \n2. **Term Mapping**: Create a concordance of “deduction” and equivalents in original languages (e.g., *deductio*, *déduction*, *Ableitung*) and track semantic shifts.  \n3. **Argument Reconstruction**: Diagram deductive structures (e.g., Descartes’Cogito → God → external world; Hume’s “is-ought” critique of moral deduction).  \n4. **Conceptual Analysis**: Compare how each thinker handles the *gap* between premises and conclusion—e.g., Leibniz’s principle of contradiction vs. Hume’s principle of resemblance.  \n5. **Influence Tracking**: Trace how pre-Kantian views of deduction inform Kant’s *Transcendental Deduction* (e.g., critique of Hume’s “mere psychological” account of causality).\n\n**5. Expected Outcomes**  \n- Clarification of why “deduction” was insufficient for Kant’s project: rationalist deduction yielded empty formalisms; empiricist deduction couldn’t ground synthetic *a priori* knowledge.  \n- A nuanced map of how empiricism *redefined* deduction as formal/logical rather than epistemic, paving the way for analytic philosophy.  \n- Resolution of common misconceptions (e.g., that Locke “endorsed deduction” like rationalists; that Hume rejected all reasoning).  \n- A historically grounded framework for evaluating modern claims about “deductive reasoning” in cognitive science or AI—by exposing their historical contingency.\n\n---\n\n#", "elaboration": "— Elaboration\n\n**Supporting Evidence**  \n- Descartes (*Meditation II*): “*Ego cogito, ergo sum*” is not a syllogism but a *direct inference* (*consequentia*) from inner awareness—showing rationalist deduction prioritizes immediacy over form.  \n- Hume (*Treatise* I.3.1): Causal inference is “a kind of *acceleration* of the mind” from one idea to another—*not* deduction, but *association*.  \n- Leibniz (*Discourse*, §13): “All truths are reducible to identities”—deduction is the unfolding of necessary connections already present in concepts.  \n- Locke (*Essay* IV.17.4): “Deduction” in moral philosophy is possible only if based on “*real* ideas,” but such ideas are scarce—revealing empiricist skepticism about substantive deduction.\n\n**Broader Implications**  \n- **Epistemology**: The rationalist-empiricist dispute over deduction exposes the tension between foundationalism and coherentism—a legacy still active in contemporary debates (e.g., BonJour vs. Rorty).  \n- **Methodology**: Hume’s restriction of deduction to “relations of ideas” anticipates logical positivism and the analytic/synthetic distinction.  \n- **Philosophy of Science**: Newton’s *regulae philosophandi* (e.g., “We are to admit no more causes of natural things than such as are both true and sufficient”) reflects a *hypothetico-deductive* model emerging *between* rationalism and empiricism—suggesting deduction was already being rethought as a tool for theory testing, not first-principle derivation.\n\n**Stakeholder Perspectives**  \n- **Academic Philosophers (U.S.)**: May view pre-Kantian deduction as a “pre-scientific” confusion—yet this ignores how Hume’s critique underpins modern scientific methodology (e.g., falsifiability as anti-dogmatic deduction).  \n- **Arkansas Educators (HS/University)**: Could use this topic to teach critical thinking by contrasting deductive certainty (geometry) with empirical uncertainty (biology)—linking to Arkansas’s strong agricultural and biomedical research sectors (e.g., UAMS).  \n- **Policy Makers**: Would benefit from understanding how historical conceptions of deduction shape public trust in science—e.g., climate modeling relies on *probabilistic* deduction, not Cartesian certainty.  \n- **Religious Groups in Arkansas**: May resonate with Descartes’ use of deduction to prove God’s existence—yet Hume’s critique challenges literalist interpretations of divine causality.\n\n**Measurable Indicators of Success (Arkansas-Specific)**  \n1. **Curriculum Integration**: At least 3 high school AP Philosophy or university ethics/science courses in Arkansas (e.g., University of Arkansas, Arkansas State) incorporate a module on pre-Kantian deduction by 2026.  \n2. **Public Engagement**: 2 public lectures (e.g., via Arkansas Humanities Program) on “Deduction and Decision-Making: Lessons from Hume and Descartes” reaching ≥500 attendees total.  \n3. **Research Output**: 1–2 peer-reviewed articles by Arkansas-based scholars on “Empiricism and Deductive Reasoning in Early Modern Thought,” indexed in Scopus/PhilPapers.  \n4. **Interdisciplinary Impact**: A workshop at UAMS or FAU (First Arkansas University) exploring how Humean critiques of causal deduction inform medical diagnostics or AI ethics in healthcare.  \n5. **Student Assessment**: 80% of students in participating courses can correctly distinguish rationalist vs. empiricist accounts of deduction on a validated concept inventory (e.g., adapted from the *Conceptual Assessment of Scientific Reasoning*).\n\nBy grounding this investigation in textual fidelity and Arkansas’s educational and research ecosystem, we transform a historical-philosophical problem into a living intellectual resource—preparing citizens to navigate the epistemic challenges of the 21st century.\n\n---\n\n**Note on the Arkansas Constraint**:  \nThe specification of “Arkansas (population 3,011,524)” is clearly an anachronistic or hypothetical device—Arkansas was admitted to the Union in 1836, long after the pre-Kantian period (c. 1600–1780). However, this framing invites *applied* relevance: how does understanding the history of deduction serve contemporary communities? In Arkansas—where debates over evolution, climate science, and AI ethics are increasingly salient—clarifying what “deduction” can and cannot do fosters epistemic resilience. The population figure may signal a desire to anchor philosophy in *local* stakes, not just Eurocentric abstraction. This response honors that by linking conceptual rigor to Arkansas’s educational and civic infrastructure.", "finding": "### Part 1 — Investigation\n\n**1. Current Understanding**  \nThe concept of *deduction* in pre-Kantian rationalism and empiricism is fundamentally shaped by divergent epistemological commitments:  \n\n- **Rationalism (Descartes, Spinoza, Leibniz)**: Deduction is understood as *a priori* reasoning from self-evident first principles (e.g., innate ideas, clear and distinct perceptions, logical axioms) to necessary truths. For Descartes, deduction mirrors geometric proof—rigorous, deductive chains from indubitable foundations. Spinoza’s *geometrical method* in the *Ethics* exemplifies deduction as the"}}